Workbook

Sheet 导读
A1: 黑灯实验室 / 自驱动实验室 / 科学智能体：1000项关键技术与思维模型
A3: 公开资料综合调研版｜截至 2026-06-18｜25个技术域 × 40项 = 1000项
A5: 口径 | B5: 定义 | C5: 核心区分 | D5: 代表来源 | F5: 本清单的使用边界
A6: 黑灯实验室（Lights-out Lab） | B6: 以AI、机器人、物联网、自动化仪器和数据平台实现少人/无人值守、可连续运行的实验设施。 | C6: 重点是无人值守执行与运营；不必然具备自主提出假设或改变研究策略的能力。 | D6: S56; S57; S63 | F6: 本工作簿不是声称穷尽全球每一家实验室或每一篇论文，而是把公开的黑灯实验室、自驱动实验室、科学自动化、AI for Science 与 Agent 技术栈，按系统工程方式尽可能全面地分解为1000个可检索、可评审的技术点。 建议用法：①按“宏观层/技术域/技术簇”筛选；②以P0建立最小闭环；③用指标列定义验收证据；④沿来源ID回到原始文献；⑤在具体行业中补充SOP、法规、仪器和风险边界。
A7: 自驱动实验室（SDL） | B7: 把自动实验、在线分析、机器学习/优化和反馈决策闭合成“设计—执行—学习—再设计”循环。 | C7: 重点是根据新证据自主选择下一实验；科学自主度高于固定脚本自动化。 | D7: S01; S02; S05; S07
A8: 科学智能体 / Agent | B8: 能感知上下文、规划任务、调用文献/数据库/代码/仿真/仪器工具、验证结果并维护记忆的软件或具身智能体。 | C8: 语言推理必须与工具权限、结构化协议、验证器、安全策略和审计轨迹共同工作。 | D8: S11; S31–S39
A11: 清单总数 | B11: 技术域 | C11: 宏观层 | D11: 来源条目 | E11: 代表系统 | F11: P0项 | G11: P1项 | H11: P2项
A12: =COUNTA('1000清单'!$A$2:$A$1001) -> 1000 | B12: =COUNTA(分类地图!$A$2:$A$26) -> 25 | C12: 7 | D12: =COUNTA(来源索引!$A$2:$A$66) -> 65 | E12: =COUNTA(代表性系统!$A$2:$A$26) -> 25 | F12: =COUNTIF('1000清单'!$K$2:$K$1001,"P0") -> 250 | G12: =COUNTIF('1000清单'!$K$2:$K$1001,"P1") -> 450 | H12: =COUNTIF('1000清单'!$K$2:$K$1001,"P2") -> 300
A15: 宏观层 | B15: 条目数
A16: 科研闭环与自主架构 | B16: =COUNTIF('1000清单'!$B$2:$B$1001,A16) -> 80
A17: 实验执行与具身自动化 | B17: =COUNTIF('1000清单'!$B$2:$B$1001,A17) -> 320
A18: 数据与互操作基础设施 | B18: =COUNTIF('1000清单'!$B$2:$B$1001,A18) -> 80
A19: 实验设计与闭环优化 | B19: =COUNTIF('1000清单'!$B$2:$B$1001,A19) -> 160
A20: 科学AI、仿真与数字孪生 | B20: =COUNTIF('1000清单'!$B$2:$B$1001,A20) -> 80
A21: 科学智能体与多智能体 | B21: =COUNTIF('1000清单'!$B$2:$B$1001,A21) -> 120
A22: 可信、安全、运营与思维模型 | B22: =COUNTIF('1000清单'!$B$2:$B$1001,A22) -> 160
A24: 七条落地判断：真正的黑灯/自驱动实验室不是“机器人+大模型”的简单叠加
A25: 1 | B25: 闭环优先 | C25: 先定义目标、证据、约束、异常和停止条件，再选硬件与模型。 | D25: S01; S02
A26: 2 | B26: 数据优先 | C26: 没有唯一身份、元数据、时间同步、溯源和质量规则，闭环只会放大噪声。 | D26: S23–S25
A27: 3 | B27: 互操作优先 | C27: 设备能力应通过稳定标准接口暴露，协议与设备解耦。 | D27: S26; S29; S30
A28: 4 | B28: 验证优先 | C28: Agent的计划、工具调用和实验动作都需要前置/后置验证与拒绝机制。 | D28: S11; S31–S39
A29: 5 | B29: 安全包络 | C29: 自主权应随证据、风险、异常和系统健康动态调整，高风险动作必须人工授权。 | D29: S46–S51
A30: 6 | B30: 指标闭环 | C30: 用样本效率、发现率、人工干预、单位成功成本、复现率和安全事件评价，而非只看吞吐。 | D30: S03; S04
A31: 7 | B31: 从P0到规模化 | C31: 先建立一个可复现的最小闭环，再逐步扩展模态、设备、Agent和跨实验室协作。 | D31: S05; S58; S60

Sheet 1000清单
A1: 编号 | B1: 宏观层 | C1: 一级技术域 | D1: 二级技术簇 | E1: 类型 | F1: 关键技术 / 思维模型 | G1: 核心技术点 | H1: 工程化验收问题 | I1: 典型指标 / 证据 | J1: 成熟度 | K1: 优先级 | L1: 代表来源ID | M1: 主来源URL
A2: T0001 | B2: 科研闭环与自主架构 | C2: 科学闭环与自主科研范式 | D2: 目标与假设 | E2: 科研范式 | F2: 目标形式化 | G2: 把“目标形式化”嵌入假设—设计—执行—分析—更新的科学闭环，使系统基于证据而非脚本机械推进研究。 | H2: 闭环输入、可证伪假设、更新规则与停止条件是否明确？ | I2: 闭环周期；样本效率；人工干预率；假设命中率；独立重复通过率 | J2: 基础能力 | K2: P0 | L2: S01; S02; S05; S07; S11 | M2: https://pubs.acs.org/doi/10.1021/acs.chemrev.4c00055
A3: T0002 | B3: 科研闭环与自主架构 | C3: 科学闭环与自主科研范式 | D3: 目标与假设 | E3: 科研范式 | F3: 假设生成 | G3: 把“假设生成”嵌入假设—设计—执行—分析—更新的科学闭环，使系统基于证据而非脚本机械推进研究。 | H3: 闭环输入、可证伪假设、更新规则与停止条件是否明确？ | I3: 闭环周期；样本效率；人工干预率；假设命中率；独立重复通过率 | J3: 基础能力 | K3: P0 | L3: S01; S02; S05; S07; S11 | M3: https://royalsocietypublishing.org/rsos/article/12/7/250646/235354/Autonomous-self-driving-laboratories-a-review-of
A4: T0003 | B4: 科研闭环与自主架构 | C4: 科学闭环与自主科研范式 | D4: 目标与假设 | E4: 科研范式 | F4: 文献证据检索 | G4: 把“文献证据检索”嵌入假设—设计—执行—分析—更新的科学闭环，使系统基于证据而非脚本机械推进研究。 | H4: 闭环输入、可证伪假设、更新规则与停止条件是否明确？ | I4: 闭环周期；样本效率；人工干预率；假设命中率；独立重复通过率 | J4: 基础能力 | K4: P0 | L4: S01; S02; S05; S07; S11 | M4: https://www.science.org/doi/10.1126/scirobotics.aat5559
A5: T0004 | B5: 科研闭环与自主架构 | C5: 科学闭环与自主科研范式 | D5: 目标与假设 | E5: 科研范式 | F5: 知识缺口识别 | G5: 把“知识缺口识别”嵌入假设—设计—执行—分析—更新的科学闭环，使系统基于证据而非脚本机械推进研究。 | H5: 闭环输入、可证伪假设、更新规则与停止条件是否明确？ | I5: 闭环周期；样本效率；人工干预率；假设命中率；独立重复通过率 | J5: 基础能力 | K5: P0 | L5: S01; S02; S05; S07; S11 | M5: https://www.nature.com/articles/s41586-023-06734-w
A6: T0005 | B6: 科研闭环与自主架构 | C6: 科学闭环与自主科研范式 | D6: 目标与假设 | E6: 科研范式 | F6: 目标—约束翻译 | G6: 把“目标—约束翻译”嵌入假设—设计—执行—分析—更新的科学闭环，使系统基于证据而非脚本机械推进研究。 | H6: 闭环输入、可证伪假设、更新规则与停止条件是否明确？ | I6: 闭环周期；样本效率；人工干预率；假设命中率；独立重复通过率 | J6: 基础能力 | K6: P0 | L6: S01; S02; S05; S07; S11 | M6: https://www.nature.com/articles/s41586-023-06792-0
A7: T0006 | B7: 科研闭环与自主架构 | C7: 科学闭环与自主科研范式 | D7: 目标与假设 | E7: 科研范式 | F7: 实验空间定义 | G7: 把“实验空间定义”嵌入假设—设计—执行—分析—更新的科学闭环，使系统基于证据而非脚本机械推进研究。 | H7: 闭环输入、可证伪假设、更新规则与停止条件是否明确？ | I7: 闭环周期；样本效率；人工干预率；假设命中率；独立重复通过率 | J7: 基础能力 | K7: P0 | L7: S01; S02; S05; S07; S11 | M7: https://pubs.acs.org/doi/10.1021/acs.chemrev.4c00055
A8: T0007 | B8: 科研闭环与自主架构 | C8: 科学闭环与自主科研范式 | D8: 目标与假设 | E8: 科研范式 | F8: 候选生成 | G8: 把“候选生成”嵌入假设—设计—执行—分析—更新的科学闭环，使系统基于证据而非脚本机械推进研究。 | H8: 闭环输入、可证伪假设、更新规则与停止条件是否明确？ | I8: 闭环周期；样本效率；人工干预率；假设命中率；独立重复通过率 | J8: 基础能力 | K8: P0 | L8: S01; S02; S05; S07; S11 | M8: https://royalsocietypublishing.org/rsos/article/12/7/250646/235354/Autonomous-self-driving-laboratories-a-review-of
A9: T0008 | B9: 科研闭环与自主架构 | C9: 科学闭环与自主科研范式 | D9: 目标与假设 | E9: 科研范式 | F9: 实验协议生成 | G9: 把“实验协议生成”嵌入假设—设计—执行—分析—更新的科学闭环，使系统基于证据而非脚本机械推进研究。 | H9: 闭环输入、可证伪假设、更新规则与停止条件是否明确？ | I9: 闭环周期；样本效率；人工干预率；假设命中率；独立重复通过率 | J9: 基础能力 | K9: P0 | L9: S01; S02; S05; S07; S11 | M9: https://www.science.org/doi/10.1126/scirobotics.aat5559
A10: T0009 | B10: 科研闭环与自主架构 | C10: 科学闭环与自主科研范式 | D10: 目标与假设 | E10: 科研范式 | F10: 试验设计 | G10: 把“试验设计”嵌入假设—设计—执行—分析—更新的科学闭环，使系统基于证据而非脚本机械推进研究。 | H10: 闭环输入、可证伪假设、更新规则与停止条件是否明确？ | I10: 闭环周期；样本效率；人工干预率；假设命中率；独立重复通过率 | J10: 基础能力 | K10: P0 | L10: S01; S02; S05; S07; S11 | M10: https://www.nature.com/articles/s41586-023-06734-w
A11: T0010 | B11: 科研闭环与自主架构 | C11: 科学闭环与自主科研范式 | D11: 目标与假设 | E11: 科研范式 | F11: 仿真预筛 | G11: 把“仿真预筛”嵌入假设—设计—执行—分析—更新的科学闭环，使系统基于证据而非脚本机械推进研究。 | H11: 闭环输入、可证伪假设、更新规则与停止条件是否明确？ | I11: 闭环周期；样本效率；人工干预率；假设命中率；独立重复通过率 | J11: 基础能力 | K11: P0 | L11: S01; S02; S05; S07; S11 | M11: https://www.nature.com/articles/s41586-023-06792-0
A12: T0011 | B12: 科研闭环与自主架构 | C12: 科学闭环与自主科研范式 | D12: 执行与分析闭环 | E12: 科研范式 | F12: 自动执行 | G12: 把“自动执行”嵌入假设—设计—执行—分析—更新的科学闭环，使系统基于证据而非脚本机械推进研究。 | H12: 闭环输入、可证伪假设、更新规则与停止条件是否明确？ | I12: 闭环周期；样本效率；人工干预率；假设命中率；独立重复通过率 | J12: 基础能力 | K12: P1 | L12: S01; S02; S05; S07; S11 | M12: https://pubs.acs.org/doi/10.1021/acs.chemrev.4c00055
... A1001: T1000 | B1001: 可信、安全、运营与思维模型 | C1001: 关键思维模型 | D1001: 韧性、证据与可证伪性 | E1001: 思维模型 | F1001: 先复现后扩展 | G1001: 把“先复现后扩展”作为设计与决策的认知透镜，用于界定问题、管理不确定性、组织证据并避免局部最优。 | H1001: 该模型在什么条件下有效，何时会误导，如何用证据校正？ | I1001: 决策可解释性；反例覆盖；假设更新速度；错误发现提前量；跨场景迁移效果 | J1001: 前沿能力 | K1001: P2 | L1001: S01; S22; S23; S47 | M1001: https://www.nist.gov/itl/ai-risk-management-framework

Sheet 分类地图
A1: 序号 | B1: 宏观层 | C1: 一级技术域 | D1: 条目数 | E1: 二级簇1 | F1: 二级簇2 | G1: 二级簇3 | H1: 二级簇4 | I1: 核心目标 | J1: 推荐牵头角色 | K1: 代表来源ID
A2: 1 | B2: 科研闭环与自主架构 | C2: 科学闭环与自主科研范式 | D2: =COUNTIF('1000清单'!$C$2:$C$1001,C2) -> 40 | E2: 目标与假设 | F2: 执行与分析闭环 | G2: 学习与决策 | H2: 人机监督与证据 | I2: 把科学问题变成可证伪、可更新、可停止的机器闭环 | J2: 首席科学家 / AI科学家 | K2: S01; S02; S05; S07; S11
A3: 2 | B3: 科研闭环与自主架构 | C3: 自主等级与系统架构 | D3: =COUNTIF('1000清单'!$C$2:$C$1001,C3) -> 40 | E3: 自主分级与控制范式 | F3: 软件架构与执行模型 | G3: 云边与分布式实验 | H3: 安全、可观测与成熟度 | I3: 建立从单设备自动化到跨实验室自主系统的架构边界 | J3: 系统架构师 / 自动化负责人 | K3: S01; S02; S04; S05; S58
A4: 3 | B4: 实验执行与具身自动化 | C4: 实验流程与机器可执行协议 | D4: =COUNTIF('1000清单'!$C$2:$C$1001,C4) -> 40 | E4: 协议语义与类型系统 | F4: 控制流与资源约束 | G4: 验证、版本与复用 | H4: 自然语言、设备映射与合规 | I4: 把SOP转成语义明确、可验证、可重放的执行协议 | J4: 实验信息学 / 协议工程师 | K4: S01; S05; S25; S26; S59
A5: 4 | B5: 实验执行与具身自动化 | C5: 机器人操作与具身技能 | D5: =COUNTIF('1000清单'!$C$2:$C$1001,C5) -> 40 | E5: 机器人本体与工具 | F5: 标定、规划与控制 | G5: 典型实验操作 | H5: 复杂环境与自恢复 | I5: 让机器人可靠完成精细、接触丰富且易污染的实验动作 | J5: 机器人与控制工程师 | K5: S08; S09; S10; S17; S61
A6: 5 | B6: 实验执行与具身自动化 | C6: 移动机器人、物流与多机器人 | D6: =COUNTIF('1000清单'!$C$2:$C$1001,C6) -> 40 | E6: 导航定位与设施 | F6: 车队与多机器人协调 | G6: 样品物流与交接 | H6: 风险、共域与韧性 | I6: 连接设备孤岛并保持样品监管链与多机器人协同 | J6: 机器人/设施物流工程师 | K6: S08; S09; S10; S12
A7: 6 | B7: 实验执行与具身自动化 | C7: 液体处理与微流控 | D7: =COUNTIF('1000清单'!$C$2:$C$1001,C7) -> 40 | E7: 计量与液体物性 | F7: 污染、耗材与感知 | G7: 工作流单元操作 | H7: 微流控与闭环控制 | I7: 将液体物性、计量、耗材和流体控制纳入闭环 | J7: 液体工作站与微流控工程师 | K7: S01; S02; S17; S18
A8: 7 | B8: 实验执行与具身自动化 | C8: 固体、粉体与合成自动化 | D8: =COUNTIF('1000清单'!$C$2:$C$1001,C8) -> 40 | E8: 粉体计量与物性 | F8: 固体加工与热处理 | G8: 固相/结晶合成 | H8: 分析制样、标识与废物 | I8: 解决粉体/固体操作难标定、难感知、批间差异大的问题 | J8: 材料合成与机电工程师 | K8: S07; S10; S17; S18
A9: 8 | B9: 实验执行与具身自动化 | C9: 反应工程、流动化学与环境控制 | D9: =COUNTIF('1000清单'!$C$2:$C$1001,C9) -> 40 | E9: 反应器与过程变量 | F9: 模型、监测与控制 | G9: 反应模态与多相体系 | H9: 环境、公用工程与放大 | I9: 把反应工程、过程控制、安全和放大统一到过程窗口 | J9: 反应工程师 / 过程控制工程师 | K9: S01; S19; S20; S58
A10: 9 | B10: 实验执行与具身自动化 | C10: 在线检测、分析仪器与计量 | D10: =COUNTIF('1000清单'!$C$2:$C$1001,C10) -> 40 | E10: PAT与光谱 | F10: 色谱、质谱与结构分析 | G10: 显微、粒径与电化学 | H10: 基础传感与计量溯源 | I10: 获得可校准、可同步、可追溯且机器可用的测量信号 | J10: 分析化学 / 计量负责人 | K10: S01; S03; S07; S19
A11: 10 | B11: 实验执行与具身自动化 | C11: 机器视觉、多模态感知与异常检测 | D11: =COUNTIF('1000清单'!$C$2:$C$1001,C11) -> 40 | E11: 成像标定与几何感知 | F11: 对象、液体与粉体视觉 | G11: 过程、安全与动作验收 | H11: 多模态、异常与主动感知 | I11: 让视觉与多模态感知成为动作验收和异常处置的反馈层 | J11: 机器视觉 / 多模态感知工程师 | K11: S09; S52; S53; S62
A12: 11 | B12: 数据与互操作基础设施 | C12: 数据基础设施、FAIR、语义与溯源 | D12: =COUNTIF('1000清单'!$C$2:$C$1001,C12) -> 40 | E12: FAIR、元数据与语义 | F12: 标识、时间与溯源 | G12: 存储与数据平台 | H12: 质量、完整性与机器可行动 | I12: 构建可发现、可互操作、可复用、可审计的数据底座 | J12: 数据架构师 / 科学数据管家 | K12: S23; S24; S25; S27; S28
A13: 12 | B13: 数据与互操作基础设施 | C13: 互操作、中间件、编排与调度 | D13: =COUNTIF('1000清单'!$C$2:$C$1001,C13) -> 40 | E13: 标准与通信协议 | F13: 设备抽象与事件架构 | G13: 一致性、锁与资源调度 | H13: 工作流、可观测与部署 | I13: 以标准接口和调度层打通异构设备、软件与资源 | J13: 软件平台 / OT集成 / 调度工程师 | K13: S05; S26; S29; S30
... A26: 25 | B26: 可信、安全、运营与思维模型 | C26: 关键思维模型 | D26: =COUNTIF('1000清单'!$C$2:$C$1001,C26) -> 40 | E26: 科学与决策闭环 | F26: 系统与学习循环 | G26: 分解、约束与架构 | H26: 韧性、证据与可证伪性 | I26: 用可迁移的认知框架管理复杂系统和科学不确定性 | J26: 科研负责人 / 系统设计评审组 | K26: S01; S22; S23; S47
A29: 宏观层 | B29: 条目数 | C29: 占比
A30: 科研闭环与自主架构 | B30: =COUNTIF('1000清单'!$B$2:$B$1001,A30) -> 80 | C30: =B30/1000 -> 0.08
A31: 实验执行与具身自动化 | B31: =COUNTIF('1000清单'!$B$2:$B$1001,A31) -> 320 | C31: =B31/1000 -> 0.32
A32: 数据与互操作基础设施 | B32: =COUNTIF('1000清单'!$B$2:$B$1001,A32) -> 80 | C32: =B32/1000 -> 0.08
A33: 实验设计与闭环优化 | B33: =COUNTIF('1000清单'!$B$2:$B$1001,A33) -> 160 | C33: =B33/1000 -> 0.16
A34: 科学AI、仿真与数字孪生 | B34: =COUNTIF('1000清单'!$B$2:$B$1001,A34) -> 80 | C34: =B34/1000 -> 0.08
A35: 科学智能体与多智能体 | B35: =COUNTIF('1000清单'!$B$2:$B$1001,A35) -> 120 | C35: =B35/1000 -> 0.12
A36: 可信、安全、运营与思维模型 | B36: =COUNTIF('1000清单'!$B$2:$B$1001,A36) -> 160 | C36: =B36/1000 -> 0.16

Sheet 代表性系统
A1: 序号 | B1: 系统 / 平台 | C1: 年份 | D1: 领域 | E1: 架构亮点 | F1: 自主闭环方式 | G1: 关键限制 / 启示 | H1: 来源ID | I1: 来源URL
A2: 1 | B2: ChemOS | C2: 2018 | D2: 跨领域编排平台 | E2: 设备抽象 + 优化器 + 工作流编排 | F2: 由优化器选择实验，平台调度设备并回传结果 | G2: 证明“操作系统层”是SDL核心，不等同于单台机器人 | H2: S05 | I2: https://www.science.org/doi/10.1126/scirobotics.aat5559
A3: 2 | B3: Ada | C3: 2020 | D3: 薄膜/材料 | E3: 自动沉积、表征与多目标闭环 | F3: 贝叶斯优化推进材料性质Pareto前沿 | G3: 多目标指标与测量质量决定闭环价值 | H3: S06 | I3: https://www.science.org/doi/10.1126/sciadv.aaz8867
A4: 3 | B4: Mobile Robotic Chemist | C4: 2020 | D4: 化学/材料 | E4: 移动机器人使用人类实验室设备 | F4: 在多工位间自主执行并按算法选择实验 | G4: 柔性高，但导航、对接与动作恢复要求极高 | H4: S08 | I4: https://www.nature.com/articles/s41586-020-2442-2
A5: 4 | B5: On-the-fly Closed-loop Materials Discovery | C5: 2020 | D5: 材料 | E5: 实时表征 + 贝叶斯主动学习 | F5: 边测边更新模型并选择下一个样品 | G5: 在线延迟和仪器同步是关键 | H5: S15 | I5: https://www.nature.com/articles/s41467-020-19597-w
A6: 5 | B6: BEAR | C6: 2020 | D6: 材料/化学 | E6: 贝叶斯实验研究员 + 自动平台 | F6: 以实验结果更新代理模型并继续搜索 | G6: 需要把实验失败作为模型可学习信号 | H6: S13 | I6: https://www.science.org/doi/10.1126/sciadv.aaz1708
A7: 6 | B7: Hierarchical Active-learning SDL | C7: 2021 | D7: 黏合材料 | E7: 分层搜索空间与主动学习 | F7: 多层变量选择和实验执行闭环 | G7: 层级变量需要显式表示和条件约束 | H7: S14 | I7: https://www.science.org/doi/10.1126/sciadv.abg4930
A8: 7 | B8: A-Lab | C8: 2023 | D8: 无机材料 | E8: 合成、热处理、XRD与计算数据库闭环 | F8: 依据计算候选自主合成并解析产物 | G8: 粉体、相鉴定和失败路线是难点 | H8: S07 | I8: https://www.nature.com/articles/s41586-023-06734-w
A9: 8 | B9: Coscientist | C9: 2023 | D9: 化学Agent | E9: LLM规划、网页/文献、代码与自动化工具 | F9: 从自然语言目标生成计划并调用实验工具 | G9: 大模型必须由工具权限、验证器和安全边界约束 | H9: S11 | I9: https://www.nature.com/articles/s41586-023-06792-0
A10: 9 | B10: AI-driven Robotic Chemist | C10: 2023 | D10: 化学合成 | E10: 机器人操作 + AI实验决策 | F10: 自主选择条件、执行并分析结果 | G10: 动作层和决策层的错误需分层诊断 | H10: S17 | I10: https://www.science.org/doi/10.1126/sciadv.adj0461
A11: 10 | B11: Autonomous Multi-property Molecular Discovery | C11: 2023 | D11: 分子发现 | E11: 合成/筛选与多性质优化 | F11: 在多属性约束下迭代候选 | G11: 需兼顾可合成性、性质冲突与测量成本 | H11: S16 | I11: https://www.science.org/doi/10.1126/science.adi1407
A12: 11 | B12: ACDC | C12: 2024 | D12: 分布式化学 | E12: 多个自动实验节点协同 | F12: 跨实验室分配任务并聚合结果 | G12: 互操作、样品/数据身份和时钟一致性最关键 | H12: S12 | I12: https://www.science.org/doi/10.1126/science.adk9227
A13: 12 | B13: Autonomous Mobile Robots for Synthetic Chemistry | C13: 2024 | D13: 有机合成 | E13: 移动操作、多设备与探索性化学 | F13: 机器人跨设备完成复杂合成工作流 | G13: 柔性执行必须配套视觉验收和异常恢复 | H13: S09 | I13: https://www.nature.com/articles/s41586-024-08173-7
... A26: 25 | B26: ADePT | C26: 2026 | D26: SDL评估框架 | E26: 从自动化、实验设计、过程和任务评估系统 | F26: 比较不同SDL能力与成熟度 | G26: 统一评估语言有助于避免营销式“全自主”表述 | H26: S04 | I26: https://www.nature.com/articles/s42004-026-01932-9

Sheet 来源索引
A1: 来源ID | B1: 文献 / 标准 / 平台 | C1: 年份 | D1: 类型 | E1: 与本清单的关系 | F1: URL
A2: S01 | B2: Self-Driving Laboratories for Chemistry and Materials Science | C2: 2024 | D2: 综述 | E2: SDL全栈、闭环、硬件、软件与挑战 | F2: https://pubs.acs.org/doi/10.1021/acs.chemrev.4c00055
A3: S02 | B3: Autonomous self-driving laboratories: a review of challenges and opportunities | C3: 2025 | D3: 综述 | E3: 自主实验室定义、架构、挑战与机会 | F3: https://royalsocietypublishing.org/rsos/article/12/7/250646/235354/Autonomous-self-driving-laboratories-a-review-of
A4: S03 | B4: Performance metrics to unleash the power of self-driving labs in chemistry and materials science | C4: 2024 | D4: 指标框架 | E4: SDL绩效、加速与增强指标 | F4: https://www.nature.com/articles/s41467-024-45569-5
A5: S04 | B5: ADePT: assessing automation, experimental design, process and task in SDLs | C5: 2026 | D5: 评估框架 | E5: 自主实验室成熟度与任务评估 | F5: https://www.nature.com/articles/s42004-026-01932-9
A6: S05 | B6: ChemOS: Orchestrating autonomous experimentation | C6: 2018 | D6: 平台论文 | E6: 实验编排、优化与设备抽象 | F6: https://www.science.org/doi/10.1126/scirobotics.aat5559
A7: S06 | B7: A self-driving laboratory advances the Pareto front for material properties | C7: 2020 | D7: 系统论文 | E7: Ada薄膜闭环与多目标优化 | F7: https://www.science.org/doi/10.1126/sciadv.aaz8867
A8: S07 | B8: Autonomous discovery of inorganic materials with A-Lab | C8: 2023 | D8: 系统论文 | E8: 无机材料合成、表征和闭环决策 | F8: https://www.nature.com/articles/s41586-023-06734-w
A9: S08 | B9: A mobile robotic chemist | C9: 2020 | D9: 系统论文 | E9: 移动机器人跨仪器自主化学实验 | F9: https://www.nature.com/articles/s41586-020-2442-2
A10: S09 | B10: Autonomous mobile robots for exploratory synthetic chemistry | C10: 2024 | D10: 系统论文 | E10: 移动操作、多工位与合成探索 | F10: https://www.nature.com/articles/s41586-024-08173-7
A11: S10 | B11: Modular, multi-robot integration for autonomous solid-state chemistry | C11: 2024 | D11: 系统论文 | E11: 模块化多机器人固相化学 | F11: https://pubs.rsc.org/en/content/articlehtml/2024/sc/d3sc06206f
A12: S11 | B12: Autonomous chemical research with large language models (Coscientist) | C12: 2023 | D12: 系统论文 | E12: LLM规划、工具调用与化学实验 | F12: https://www.nature.com/articles/s41586-023-06792-0
... A66: S65 | B66: AILA: an AI laboratory agent for autonomous functional materials research | C66: 2025 | D66: 科学Agent论文 | E66: 多Agent、文献、实验与材料研究协同 | F66: https://www.nature.com/articles/s41467-025-64105-7
